LICENSE.txt
MANIFEST.in
README.rst
release-history.rst
requirements.txt
setup.py
potplayer/__init__.py
potplayer/execute.py
potplayer/playlist.py
potplayer/zzz_manual_install.py
potplayer.egg-info/PKG-INFO
potplayer.egg-info/SOURCES.txt
potplayer.egg-info/dependency_links.txt
potplayer.egg-info/top_level.txt
potplayer/__pycache__/__init__.cpython-33.pyc
potplayer/__pycache__/execute.cpython-33.pyc
potplayer/__pycache__/playlist.cpython-33.pyc