Metadata-Version: 1.1
Name: potplayer
Version: 0.0.3
Summary: A tools to manipulate potplayer playlist
Home-page: https://github.com/MacHu-GWU/potplayer-project
Author: Sanhe Hu
Author-email: husanhe@gmail.com
License: MIT
Download-URL: https://github.com/MacHu-GWU/potplayer-project/tarball/2016-10-03
Platform: Windows
Platform: MacOS
Platform: Unix
Classifier: Development Status :: 4 - Beta
Classifier: Intended Audience :: Developers
Classifier: License :: OSI Approved :: MIT License
Classifier: Natural Language :: English
Classifier: Operating System :: Microsoft :: Windows
Classifier: Operating System :: MacOS
Classifier: Operating System :: Unix
Classifier: Programming Language :: Python
Classifier: Programming Language :: Python :: 2.7
Classifier: Programming Language :: Python :: 3.3
Classifier: Programming Language :: Python :: 3.4
Classifier: Programming Language :: Python :: 3.5
